cs/app/svcd.py
cs.app.svcd-20221228.dist-info/METADATA
cs.app.svcd-20221228.dist-info/WHEEL
cs.app.svcd-20221228.dist-info/entry_points.txt
cs.app.svcd-20221228.dist-info/top_level.txt
cs.app.svcd-20221228.dist-info/RECORD
