Metadata-Version: 2.1
Name: cs.app.svcd
Version: 20221228
Summary: SvcD class and "svcd" command to run persistent service programmes.
Home-page: https://bitbucket.org/cameron_simpson/css/commits/all
Author: Cameron Simpson
Author-email: Cameron Simpson <cs@cskk.id.au>
License: GNU General Public License v3 or later (GPLv3+)
Project-URL: URL, https://bitbucket.org/cameron_simpson/css/commits/all
Keywords: python2,python3
Classifier: Programming Language :: Python
Classifier: Programming Language :: Python :: 2
Classifier: Programming Language :: Python :: 3
Classifier: Topic :: Utilities
Classifier: Development Status :: 4 - Beta
Classifier: Intended Audience :: Developers
Classifier: Operating System :: OS Independent
Classifier: License :: OSI Approved :: GNU General Public License v3 or later (GPLv3+)
Requires-Dist: cs.app.flag (>=20201228)
Requires-Dist: cs.cmdutils (>=20221228)
Requires-Dist: cs.env (>=20190103)
Requires-Dist: cs.gimmicks (>=20221228)
Requires-Dist: cs.lex (>=20220918)
Requires-Dist: cs.logutils (>=20220531)
Requires-Dist: cs.pfx (>=20221118)
Requires-Dist: cs.psutils (>=20221228)
Requires-Dist: cs.sh
